[{"id":31930,"name":"Adanero","lat":40.94487,"lng":-4.60561},{"id":32055,"name":"Albornos","lat":40.83795,"lng":-4.88129},{"id":32162,"name":"Aldeanueva de Santa Cruz","lat":40.38189,"lng":-5.42142},{"id":32170,"name":"Aldeaseca","lat":41.04912,"lng":-4.81707},{"id":32348,"name":"Amavida","lat":40.57371,"lng":-5.06541},{"id":32447,"name":"Arenas de San Pedro","lat":40.21041,"lng":-5.08694},{"id":152702,"name":"Arevalillo","lat":40.5867523,"lng":-5.3723634},{"id":32531,"name":"Arévalo","lat":41.06255,"lng":-4.72042},{"id":32564,"name":"Aveinte","lat":40.78227,"lng":-4.83649},{"id":32565,"name":"Avellaneda","lat":40.38909,"lng":-5.38811},{"id":38576,"name":"Ávila","lat":40.65724,"lng":-4.69951},{"id":32680,"name":"Barromán","lat":41.06536,"lng":-4.93066},{"id":32721,"name":"Becedas","lat":40.40369,"lng":-5.63577},{"id":32722,"name":"Becedillas","lat":40.53821,"lng":-5.32561},{"id":32841,"name":"Bercial de Zapardiel","lat":41.04675,"lng":-4.9691},{"id":152706,"name":"Bernuy-Zapardiel","lat":40.9758091,"lng":-4.944831},{"id":32872,"name":"Berrocalejo de Aragona","lat":40.69436,"lng":-4.59474},{"id":32910,"name":"Blascomillán","lat":40.80146,"lng":-5.08703},{"id":152707,"name":"Blasconuño de Matacabras","lat":41.1235036,"lng":-4.9898767},{"id":32911,"name":"Blascosancho","lat":40.87744,"lng":-4.63743},{"id":32932,"name":"Bohoyo","lat":40.31584,"lng":-5.44294},{"id":32948,"name":"Bonilla de la Sierra","lat":40.53063,"lng":-5.26452},{"id":32968,"name":"Brabos","lat":40.77846,"lng":-4.93934},{"id":152709,"name":"Bularros","lat":40.724347,"lng":-4.8656771},{"id":33025,"name":"Burgohondo","lat":40.41416,"lng":-4.78509},{"id":33085,"name":"Cabezas de Alambre","lat":40.94218,"lng":-4.84184},{"id":33086,"name":"Cabezas del Pozo","lat":41.00139,"lng":-4.95453},{"id":33087,"name":"Cabezas del Villar","lat":40.71557,"lng":-5.20956},{"id":33096,"name":"Cabizuela","lat":40.9009,"lng":-4.80212},{"id":33222,"name":"Canales","lat":41.00331,"lng":-4.90163},{"id":33228,"name":"Candeleda","lat":40.15521,"lng":-5.24045},{"id":33259,"name":"Cantiveros","lat":40.95215,"lng":-4.95455},{"id":33301,"name":"Cardeñosa","lat":40.7424,"lng":-4.74579},{"id":152711,"name":"Casas del Puerto","lat":40.5288456,"lng":-5.1973119},{"id":152712,"name":"Casasola","lat":40.6686976,"lng":-4.8277621},{"id":33382,"name":"Casavieja","lat":40.28325,"lng":-4.7667},{"id":33388,"name":"Casillas","lat":40.3261,"lng":-4.57182},{"id":33417,"name":"Castellanos de Zapardiel","lat":41.0845,"lng":-4.90984},{"id":33551,"name":"Cebreros","lat":40.45835,"lng":-4.46433},{"id":33577,"name":"Cepeda la Mora","lat":40.4578,"lng":-5.04833},{"id":33614,"name":"Chamartín","lat":40.70267,"lng":-4.95769},{"id":33672,"name":"Cillán","lat":40.70675,"lng":-4.98135},{"id":33690,"name":"Cisla","lat":40.96662,"lng":-5.01405},{"id":33734,"name":"Collado de Contreras","lat":40.88743,"lng":-4.9314},{"id":33735,"name":"Collado del Mirón","lat":40.55307,"lng":-5.35398},{"id":33767,"name":"Constanzana","lat":40.93821,"lng":-4.87515},{"id":33834,"name":"Crespos","lat":40.87128,"lng":-4.97094},{"id":33879,"name":"Cuevas del Valle","lat":40.29418,"lng":-5.00938},{"id":152753,"name":"Diego del Carpio","lat":40.6634952,"lng":-5.3416255},{"id":33945,"name":"Donjimeno","lat":40.95978,"lng":-4.84627},{"id":33947,"name":"Donvidas","lat":41.08954,"lng":-4.80634},{"id":152701,"name":"El Arenal","lat":40.2738765,"lng":-5.0858988},{"id":152703,"name":"El Barco de Ávila","lat":40.3569063,"lng":-5.5236746},{"id":152704,"name":"El Barraco","lat":40.4424483,"lng":-4.5830789},{"id":152708,"name":"El Bohodón","lat":40.9155501,"lng":-4.729693},{"id":152715,"name":"El Fresno","lat":40.6137059,"lng":-4.756863},{"id":152724,"name":"El Hornillo","lat":40.2667135,"lng":-5.1327829},{"id":152725,"name":"El Hoyo de Pinares","lat":40.5007886,"lng":-4.4220673},{"id":152727,"name":"El Losar del Barco","lat":40.3938194,"lng":-5.5393011},{"id":152730,"name":"El Mirón","lat":40.5332711,"lng":-5.4050813},{"id":152734,"name":"El Oso","lat":40.8394969,"lng":-4.7698058},{"id":152735,"name":"El Parral","lat":40.7986287,"lng":-4.990298},{"id":152749,"name":"El Tiemblo","lat":40.4130828,"lng":-4.4993148},{"id":152714,"name":"Espinosa de los Caballeros","lat":41.0090149,"lng":-4.6531074},{"id":34196,"name":"Flores de Ávila","lat":40.93358,"lng":-5.07914},{"id":34217,"name":"Fontiveros","lat":40.92997,"lng":-4.96445},{"id":34248,"name":"Fresnedilla","lat":40.23233,"lng":-4.62201},{"id":152716,"name":"Fuente el Saúz","lat":40.9773051,"lng":-4.9097818},{"id":34340,"name":"Fuentes de Año","lat":41.01769,"lng":-4.89907},{"id":152717,"name":"Gallegos de Altamiros","lat":40.7115993,"lng":-4.9110829},{"id":34389,"name":"Gallegos de Sobrinos","lat":40.71693,"lng":-5.11224},{"id":34416,"name":"Garganta del Villar","lat":40.44965,"lng":-5.1042},{"id":34440,"name":"Gavilanes","lat":40.27791,"lng":-4.85321},{"id":34450,"name":"Gemuño","lat":40.59159,"lng":-4.78178},{"id":152719,"name":"Gil García","lat":40.2978672,"lng":-5.594224},{"id":152718,"name":"Gilbuena","lat":40.4158636,"lng":-5.6057168},{"id":34465,"name":"Gimialcón","lat":40.87705,"lng":-5.12308},{"id":34489,"name":"Gotarrendura","lat":40.82652,"lng":-4.7409},{"id":152720,"name":"Grandes y San Martín","lat":40.765974,"lng":-4.9714572},{"id":34551,"name":"Guisando","lat":40.22225,"lng":-5.1395},{"id":34556,"name":"Gutierre-Muñoz","lat":40.98295,"lng":-4.63839},{"id":34589,"name":"Hernansancho","lat":40.85753,"lng":-4.73045},{"id":152721,"name":"Herradón de Pinares","lat":40.5646966,"lng":-4.5592946},{"id":34600,"name":"Herreros de Suso","lat":40.80361,"lng":-5.03892},{"id":34613,"name":"Higuera de las Dueñas","lat":40.23903,"lng":-4.60361},{"id":34653,"name":"Horcajo de las Torres","lat":41.06497,"lng":-5.09092},{"id":34675,"name":"Hoyocasero","lat":40.3989,"lng":-4.97455},{"id":34676,"name":"Hoyorredondo","lat":40.4627,"lng":-5.41097},{"id":34678,"name":"Hoyos de Miguel Muñoz","lat":40.39237,"lng":-5.06713},{"id":34679,"name":"Hoyos del Collado","lat":40.35945,"lng":-5.20027},{"id":34680,"name":"Hoyos del Espino","lat":40.35623,"lng":-5.17505},{"id":34704,"name":"Hurtumpascual","lat":40.692,"lng":-5.11379},{"id":34830,"name":"Junciana","lat":40.41076,"lng":-5.55698},{"id":152699,"name":"La Adrada","lat":40.2995582,"lng":-4.6365342},{"id":152700,"name":"La Aldehuela","lat":40.4109199,"lng":-5.409336},{"id":152710,"name":"La Carrera","lat":40.3471658,"lng":-5.554509},{"id":152713,"name":"La Colilla","lat":40.6462619,"lng":-4.7659226},{"id":152722,"name":"La Hija de Dios","lat":40.5297571,"lng":-4.9672351},{"id":152723,"name":"La Horcajada","lat":40.4364872,"lng":-5.466641},{"id":152746,"name":"La Serrada","lat":40.6312093,"lng":-4.7931105},{"id":152750,"name":"La Torre","lat":40.5897295,"lng":-4.9656113},{"id":34962,"name":"Langa","lat":41.0055,"lng":-4.85946},{"id":152726,"name":"Lanzahíta","lat":40.2052477,"lng":-4.9337946},{"id":152705,"name":"Las Berlanas","lat":40.7991663,"lng":-4.7621826},{"id":152733,"name":"Las Navas del Marqués","lat":40.6018276,"lng":-4.3333954},{"id":152728,"name":"Llanos de Tormes Los","lat":40.3284461,"lng":-5.5003955},{"id":35190,"name":"Madrigal de las Altas Torres","lat":41.08968,"lng":-4.99863},{"id":35198,"name":"Maello","lat":40.80929,"lng":-4.51186},{"id":35226,"name":"Malpartida de Corneja","lat":40.52208,"lng":-5.35026},{"id":35235,"name":"Mamblas","lat":41.01925,"lng":-5.00873},{"id":35241,"name":"Mancera de Arriba","lat":40.79139,"lng":-5.14772},{"id":35252,"name":"Manjabálago","lat":40.66441,"lng":-5.07719},{"id":152729,"name":"Marlín","lat":40.7116571,"lng":-4.8290579},{"id":35299,"name":"Martiherrero","lat":40.67392,"lng":-4.78156},{"id":35309,"name":"Martínez","lat":40.63046,"lng":-5.34801},{"id":35368,"name":"Mediana de Voltoya","lat":40.70104,"lng":-4.56341},{"id":35375,"name":"Medinilla","lat":40.43967,"lng":-5.61772},{"id":35404,"name":"Mengamuñoz","lat":40.50006,"lng":-4.99983},{"id":35409,"name":"Mesegar de Corneja","lat":40.50209,"lng":-5.30131},{"id":35426,"name":"Mijares","lat":40.29655,"lng":-4.83651},{"id":35438,"name":"Mingorría","lat":40.75192,"lng":-4.66583},{"id":35455,"name":"Mironcillo","lat":40.55435,"lng":-4.82449},{"id":152731,"name":"Mirueña de los Infanzones","lat":40.7361548,"lng":-5.0904552},{"id":35491,"name":"Mombeltrán","lat":40.25987,"lng":-5.01749},{"id":35526,"name":"Monsalupe","lat":40.76953,"lng":-4.78131},{"id":35603,"name":"Moraleja de Matacabras","lat":41.10732,"lng":-4.95717},{"id":35692,"name":"Muñana","lat":40.59042,"lng":-5.01447},{"id":35693,"name":"Muñico","lat":40.70678,"lng":-5.02717},{"id":35694,"name":"Muñogalindo","lat":40.60324,"lng":-4.89895},{"id":35695,"name":"Muñogrande","lat":40.82181,"lng":-4.92223},{"id":35696,"name":"Muñomer del Peco","lat":40.85878,"lng":-4.87992},{"id":35698,"name":"Muñopepe","lat":40.63408,"lng":-4.81876},{"id":35699,"name":"Muñosancho","lat":40.92097,"lng":-5.03559},{"id":35700,"name":"Muñotello","lat":40.54236,"lng":-5.04187},{"id":35714,"name":"Narrillos del Álamo","lat":40.56673,"lng":-5.46584},{"id":35713,"name":"Narrillos del Rebollar","lat":40.66488,"lng":-4.96577},{"id":35717,"name":"Narros de Saldueña","lat":40.87268,"lng":-4.86909},{"id":35718,"name":"Narros del Castillo","lat":40.85869,"lng":-5.0601},{"id":35719,"name":"Narros del Puerto","lat":40.54131,"lng":-4.99291},{"id":35721,"name":"Nava de Arévalo","lat":40.97803,"lng":-4.77573},{"id":35727,"name":"Nava del Barco","lat":40.29321,"lng":-5.54022},{"id":35730,"name":"Navacepedilla de Corneja","lat":40.48602,"lng":-5.1838},{"id":35733,"name":"Navadijos","lat":40.42524,"lng":-5.08285},{"id":35734,"name":"Navaescurial","lat":40.47163,"lng":-5.27756},{"id":35737,"name":"Navahondilla","lat":40.3251,"lng":-4.49661},{"id":35741,"name":"Navalacruz","lat":40.43993,"lng":-4.93122},{"id":35750,"name":"Navalmoral","lat":40.46028,"lng":-4.76859},{"id":152732,"name":"Navalonguilla","lat":40.2784799,"lng":-5.5007233},{"id":35754,"name":"Navalosa","lat":40.40212,"lng":-4.92999},{"id":35755,"name":"Navalperal de Pinares","lat":40.59398,"lng":-4.41149},{"id":35756,"name":"Navalperal de Tormes","lat":40.3528,"lng":-5.30084},{"id":35759,"name":"Navaluenga","lat":40.41123,"lng":-4.70897},{"id":35764,"name":"Navaquesera","lat":40.42558,"lng":-4.91108},{"id":35771,"name":"Navarredonda de Gredos","lat":40.36136,"lng":-5.13268},{"id":35773,"name":"Navarredondilla","lat":40.45416,"lng":-4.82199},{"id":35774,"name":"Navarrevisca","lat":40.36417,"lng":-4.89352},{"id":35787,"name":"Navatalgordo","lat":40.4152,"lng":-4.87155},{"id":35788,"name":"Navatejares","lat":40.33602,"lng":-5.5322},{"id":35800,"name":"Neila de San Miguel","lat":40.42372,"lng":-5.6509},{"id":35811,"name":"Niharra","lat":40.58945,"lng":-4.83895},{"id":35869,"name":"Ojos-Albos","lat":40.70596,"lng":-4.51633},{"id":35934,"name":"Orbita","lat":40.99846,"lng":-4.64833},{"id":35990,"name":"Padiernos","lat":40.62168,"lng":-4.84523},{"id":36000,"name":"Pajares de Adaja","lat":40.92398,"lng":-4.64048},{"id":36006,"name":"Palacios de Goda","lat":41.11798,"lng":-4.78496},{"id":36051,"name":"Papatrigo","lat":40.8679,"lng":-4.83399},{"id":152736,"name":"Pascualcobo","lat":40.6557128,"lng":-5.2769333},{"id":36099,"name":"Pedro Bernardo","lat":40.24214,"lng":-4.90963},{"id":152737,"name":"Pedro-Rodríguez","lat":40.9363586,"lng":-4.7868571},{"id":36117,"name":"Peguerinos","lat":40.6262,"lng":-4.23154},{"id":36166,"name":"Peñalba de Ávila","lat":40.77266,"lng":-4.74595},{"id":152738,"name":"Piedrahíta","lat":40.4652069,"lng":-5.3272431},{"id":36182,"name":"Piedralaves","lat":40.31721,"lng":-4.70025},{"id":36306,"name":"Poveda","lat":40.56799,"lng":-5.07909},{"id":36310,"name":"Poyales del Hoyo","lat":40.17254,"lng":-5.16597},{"id":36315,"name":"Pozanco","lat":40.80095,"lng":-4.66772},{"id":36349,"name":"Pradosegar","lat":40.5502,"lng":-5.07015},{"id":36444,"name":"Puerto Castilla","lat":40.288,"lng":-5.62366},{"id":36550,"name":"Rasueros","lat":41.02344,"lng":-5.07377},{"id":152739,"name":"Riocabado","lat":40.8305303,"lng":-4.8034713},{"id":152740,"name":"Riofrío","lat":40.5485637,"lng":-4.777595},{"id":36640,"name":"Rivilla de Barajas","lat":40.9021,"lng":-4.98836},{"id":36772,"name":"Salobral","lat":40.61179,"lng":-4.81013},{"id":36781,"name":"Salvadiós","lat":40.87836,"lng":-5.09629},{"id":36807,"name":"San Bartolomé de Béjar","lat":40.40783,"lng":-5.66261},{"id":36808,"name":"San Bartolomé de Corneja","lat":40.49257,"lng":-5.38519},{"id":152741,"name":"San Bartolomé de Pinares","lat":40.5425535,"lng":-4.5398806},{"id":36831,"name":"San Esteban de los Patos","lat":40.74705,"lng":-4.62413},{"id":152742,"name":"San Esteban de Zapardiel","lat":41.0924448,"lng":-4.9003741},{"id":36833,"name":"San Esteban del Valle","lat":40.2751,"lng":-4.98215},{"id":36837,"name":"San García de Ingelmos","lat":40.76912,"lng":-5.11523},{"id":152751,"name":"San Juan de Gredos","lat":40.3638666,"lng":-5.2371087},{"id":36846,"name":"San Juan de la Encinilla","lat":40.8302,"lng":-4.83957},{"id":36847,"name":"San Juan de la Nava","lat":40.4788,"lng":-4.68238},{"id":36850,"name":"San Juan del Molinillo","lat":40.45909,"lng":-4.81711},{"id":152743,"name":"San Juan del Olmo","lat":40.653132,"lng":-5.0514117},{"id":36859,"name":"San Lorenzo de Tormes","lat":40.36984,"lng":-5.48848},{"id":36874,"name":"San Martín de la Vega del Alberche","lat":40.43053,"lng":-5.155},{"id":36876,"name":"San Martín del Pimpollar","lat":40.3683,"lng":-5.05443},{"id":36881,"name":"San Miguel de Corneja","lat":40.48722,"lng":-5.28654},{"id":36884,"name":"San Miguel de Serrezuela","lat":40.67064,"lng":-5.28857},{"id":36898,"name":"San Pascual","lat":40.88141,"lng":-4.75612},{"id":36909,"name":"San Pedro del Arroyo","lat":40.80213,"lng":-4.87075},{"id":36927,"name":"San Vicente de Arévalo","lat":40.96773,"lng":-4.80194},{"id":36935,"name":"Sanchidrián","lat":40.89347,"lng":-4.58132},{"id":36937,"name":"Sanchorreja","lat":40.66475,"lng":-4.91494},{"id":37035,"name":"Santa Cruz de Pinares","lat":40.54265,"lng":-4.58036},{"id":37045,"name":"Santa Cruz del Valle","lat":40.2516,"lng":-5.00133},{"id":37083,"name":"Santa María de los Caballeros","lat":40.38925,"lng":-5.45112},{"id":152744,"name":"Santa María del Arroyo","lat":40.6007333,"lng":-4.9230849},{"id":37084,"name":"Santa María del Berrocal","lat":40.50845,"lng":-5.40483},{"id":152752,"name":"Santa María del Cubillo","lat":40.7409663,"lng":-4.4696765},{"id":152745,"name":"Santa María del Tiétar","lat":40.3049393,"lng":-4.5534167},{"id":37118,"name":"Santiago del Collado","lat":40.43326,"lng":-5.35631},{"id":152754,"name":"Santiago del Tormes","lat":40.3368033,"lng":-5.3834854},{"id":37142,"name":"Santo Domingo de las Posadas","lat":40.812,"lng":-4.63383},{"id":37144,"name":"Santo Tomé de Zabarcos","lat":40.78726,"lng":-4.91048},{"id":37224,"name":"Serranillos","lat":40.33625,"lng":-4.91165},{"id":37251,"name":"Sigeres","lat":40.79939,"lng":-4.93361},{"id":37263,"name":"Sinlabajos","lat":41.0765,"lng":-4.83242},{"id":152747,"name":"Solana de Ávila","lat":40.3150614,"lng":-5.6135989},{"id":152748,"name":"Solana de Rioalmar","lat":40.7383593,"lng":-5.0110952},{"id":37284,"name":"Solosancho","lat":40.55294,"lng":-4.90479},{"id":37311,"name":"Sotalbo","lat":40.5417,"lng":-4.84548},{"id":37313,"name":"Sotillo de la Adrada","lat":40.2912,"lng":-4.58385},{"id":37434,"name":"Tiñosillos","lat":40.934,"lng":-4.72767},{"id":37442,"name":"Tolbaños","lat":40.75168,"lng":-4.58191},{"id":37469,"name":"Tormellas","lat":40.30404,"lng":-5.51185},{"id":37473,"name":"Tornadizos de Ávila","lat":40.62757,"lng":-4.61426},{"id":37669,"name":"Tórtoles","lat":40.5612,"lng":-5.2612},{"id":37686,"name":"Umbrías","lat":40.3153,"lng":-5.58037},{"id":37717,"name":"Vadillo de la Sierra","lat":40.60634,"lng":-5.12506},{"id":37739,"name":"Valdecasa","lat":40.65931,"lng":-5.01183},{"id":37908,"name":"Vega de Santa María","lat":40.83618,"lng":-4.64287},{"id":37925,"name":"Velayos","lat":40.84157,"lng":-4.62324},{"id":38052,"name":"Villaflor","lat":40.75865,"lng":-4.87379},{"id":38059,"name":"Villafranca de la Sierra","lat":40.49806,"lng":-5.23005},{"id":152755,"name":"Villanueva de Ávila","lat":40.3787322,"lng":-4.8216074},{"id":38185,"name":"Villanueva de Gómez","lat":40.88269,"lng":-4.7165},{"id":38211,"name":"Villanueva del Aceral","lat":41.04095,"lng":-4.85419},{"id":38214,"name":"Villanueva del Campillo","lat":40.57646,"lng":-5.18002},{"id":38237,"name":"Villar de Corneja","lat":40.47462,"lng":-5.43307},{"id":38276,"name":"Villarejo del Valle","lat":40.28638,"lng":-4.99674},{"id":38331,"name":"Villatoro","lat":40.55609,"lng":-5.11262},{"id":38409,"name":"Viñegra de Moraña","lat":40.85074,"lng":-4.92115},{"id":38401,"name":"Vita","lat":40.81178,"lng":-5.00583},{"id":38468,"name":"Zapardiel de la Cañada","lat":40.60648,"lng":-5.33791},{"id":38469,"name":"Zapardiel de la Ribera","lat":40.35554,"lng":-5.32826}]