[{"id":111006,"name":"Ada","lat":47.29969,"lng":-96.51535},{"id":111047,"name":"Adrian","lat":43.63497,"lng":-95.9328},{"id":111053,"name":"Afton","lat":44.90275,"lng":-92.78354},{"id":111073,"name":"Aitkin","lat":46.53301,"lng":-93.71025},{"id":111074,"name":"Aitkin County","lat":46.60826,"lng":-93.41543},{"id":111106,"name":"Albany","lat":45.62996,"lng":-94.57},{"id":111118,"name":"Albert Lea","lat":43.64801,"lng":-93.36827},{"id":111121,"name":"Albertville","lat":45.23774,"lng":-93.65441},{"id":111154,"name":"Alexandria","lat":45.88524,"lng":-95.37754},{"id":111324,"name":"Andover","lat":45.2333,"lng":-93.29134},{"id":111350,"name":"Annandale","lat":45.26274,"lng":-94.12443},{"id":111358,"name":"Anoka","lat":45.19774,"lng":-93.38718},{"id":111359,"name":"Anoka County","lat":45.27324,"lng":-93.24645},{"id":111393,"name":"Apple Valley","lat":44.73191,"lng":-93.21772},{"id":111396,"name":"Appleton","lat":45.19691,"lng":-96.01977},{"id":111438,"name":"Arden Hills","lat":45.05024,"lng":-93.15661},{"id":111466,"name":"Arlington","lat":44.6083,"lng":-94.08053},{"id":111486,"name":"Arnold","lat":46.88022,"lng":-92.09047},{"id":111612,"name":"Atwater","lat":45.13885,"lng":-94.77806},{"id":111660,"name":"Aurora","lat":47.52993,"lng":-92.23712},{"id":111669,"name":"Austin","lat":43.66663,"lng":-92.97464},{"id":111692,"name":"Avon","lat":45.60913,"lng":-94.45167},{"id":111714,"name":"Babbitt","lat":47.70853,"lng":-91.9446},{"id":111728,"name":"Bagley","lat":47.52162,"lng":-95.39835},{"id":111830,"name":"Barnesville","lat":46.65218,"lng":-96.41979},{"id":111911,"name":"Baudette","lat":48.71247,"lng":-94.59993},{"id":111916,"name":"Baxter","lat":46.3433,"lng":-94.28667},{"id":111951,"name":"Bayport","lat":45.02136,"lng":-92.78104},{"id":112012,"name":"Becker","lat":45.3933,"lng":-93.87692},{"id":112013,"name":"Becker County","lat":46.93465,"lng":-95.67392},{"id":112090,"name":"Belle Plaine","lat":44.62274,"lng":-93.76857},{"id":112150,"name":"Beltrami","lat":47.97378,"lng":-94.93765},{"id":112160,"name":"Bemidji","lat":47.47356,"lng":-94.88028},{"id":112183,"name":"Benson","lat":45.31496,"lng":-95.60003},{"id":112205,"name":"Benton County","lat":45.69913,"lng":-93.99884},{"id":112323,"name":"Big Lake","lat":45.33246,"lng":-93.74608},{"id":112336,"name":"Big Stone","lat":45.4261,"lng":-96.41092},{"id":112355,"name":"Birchwood","lat":45.06108,"lng":-92.97605},{"id":112403,"name":"Blaine","lat":45.1608,"lng":-93.23495},{"id":112442,"name":"Blooming Prairie","lat":43.86663,"lng":-93.05103},{"id":112452,"name":"Bloomington","lat":44.8408,"lng":-93.29828},{"id":112465,"name":"Blue Earth","lat":43.63746,"lng":-94.10218},{"id":112466,"name":"Blue Earth County","lat":44.03459,"lng":-94.06703},{"id":112679,"name":"Braham","lat":45.72274,"lng":-93.17078},{"id":112681,"name":"Brainerd","lat":46.35802,"lng":-94.20083},{"id":112684,"name":"Branch","lat":45.48524,"lng":-92.96188},{"id":112712,"name":"Breckenridge","lat":46.26357,"lng":-96.58813},{"id":112718,"name":"Breezy Point","lat":46.59001,"lng":-94.21982},{"id":112874,"name":"Brooklyn Center","lat":45.07608,"lng":-93.33273},{"id":112877,"name":"Brooklyn Park","lat":45.09413,"lng":-93.35634},{"id":112911,"name":"Brown","lat":44.24217,"lng":-94.72748},{"id":113013,"name":"Buffalo","lat":45.17191,"lng":-93.87469},{"id":113091,"name":"Burnsville","lat":44.76774,"lng":-93.27772},{"id":113145,"name":"Byron","lat":44.03274,"lng":-92.64546},{"id":113190,"name":"Caledonia","lat":43.63469,"lng":-91.49681},{"id":113253,"name":"Cambridge","lat":45.57274,"lng":-93.22439},{"id":113321,"name":"Canby","lat":44.70885,"lng":-96.27643},{"id":113334,"name":"Cannon Falls","lat":44.50691,"lng":-92.90548},{"id":113411,"name":"Carlton","lat":46.66383,"lng":-92.42491},{"id":113413,"name":"Carlton County","lat":46.5924,"lng":-92.67705},{"id":113501,"name":"Carver","lat":44.76357,"lng":-93.62579},{"id":113502,"name":"Carver County","lat":44.82076,"lng":-93.80258},{"id":113532,"name":"Cass","lat":46.94959,"lng":-94.32535},{"id":113640,"name":"Center City","lat":45.39385,"lng":-92.8166},{"id":113660,"name":"Centerville","lat":45.16302,"lng":-93.05578},{"id":113727,"name":"Champlin","lat":45.18885,"lng":-93.39745},{"id":113732,"name":"Chanhassen","lat":44.86219,"lng":-93.53079},{"id":113794,"name":"Chaska","lat":44.78941,"lng":-93.60218},{"id":113795,"name":"Chatfield","lat":43.84552,"lng":-92.18905},{"id":113974,"name":"Chippewa","lat":45.02234,"lng":-95.56669},{"id":113978,"name":"Chisago","lat":45.50247,"lng":-92.90834},{"id":113977,"name":"Chisago City","lat":45.37358,"lng":-92.88994},{"id":113979,"name":"Chisholm","lat":47.4891,"lng":-92.8838},{"id":114030,"name":"Circle Pines","lat":45.14858,"lng":-93.15161},{"id":114100,"name":"Clara City","lat":44.95496,"lng":-95.3664},{"id":114188,"name":"Clay County","lat":46.89234,"lng":-96.49065},{"id":114225,"name":"Clearwater","lat":45.41941,"lng":-94.04887},{"id":114226,"name":"Clearwater County","lat":47.57766,"lng":-95.37903},{"id":114304,"name":"Cloquet","lat":46.72161,"lng":-92.45936},{"id":114373,"name":"Cohasset","lat":47.26356,"lng":-93.62022},{"id":114376,"name":"Cokato","lat":45.0758,"lng":-94.18998},{"id":114386,"name":"Cold Spring","lat":45.4558,"lng":-94.42888},{"id":114401,"name":"Coleraine","lat":47.28883,"lng":-93.42771},{"id":114419,"name":"Collegeville","lat":45.59441,"lng":-94.36305},{"id":114442,"name":"Cologne","lat":44.77163,"lng":-93.78135},{"id":114486,"name":"Columbia Heights","lat":45.0408,"lng":-93.263},{"id":114500,"name":"Columbus","lat":45.26522,"lng":-93.05015},{"id":114593,"name":"Cook","lat":47.81684,"lng":-90.54108},{"id":114600,"name":"Coon Rapids","lat":45.11997,"lng":-93.28773},{"id":114632,"name":"Corcoran","lat":45.09524,"lng":-93.54746},{"id":114691,"name":"Cottage Grove","lat":44.82774,"lng":-92.94382},{"id":114700,"name":"Cottonwood","lat":44.60885,"lng":-95.67419},{"id":114703,"name":"Cottonwood County","lat":44.00711,"lng":-95.18115},{"id":114840,"name":"Crookston","lat":47.77414,"lng":-96.60812},{"id":114843,"name":"Crosby","lat":46.48218,"lng":-93.95776},{"id":114849,"name":"Cross Lake","lat":46.65941,"lng":-94.11387},{"id":114861,"name":"Crow Wing","lat":46.48237,"lng":-94.07087},{"id":114874,"name":"Crystal","lat":45.03274,"lng":-93.36023},{"id":114976,"name":"Dakota","lat":44.67189,"lng":-93.06544},{"id":115055,"name":"Dassel","lat":45.08163,"lng":-94.30693},{"id":115082,"name":"Dawson","lat":44.93274,"lng":-96.05448},{"id":115096,"name":"Dayton","lat":45.24385,"lng":-93.51496},{"id":115171,"name":"Deephaven","lat":44.92969,"lng":-93.52246},{"id":115198,"name":"Delano","lat":45.04191,"lng":-93.78913},{"id":115216,"name":"Dellwood","lat":45.08997,"lng":-92.97244},{"id":115293,"name":"Detroit Lakes","lat":46.81718,"lng":-95.84533},{"id":115347,"name":"Dilworth","lat":46.87663,"lng":-96.70341},{"id":115378,"name":"Dodge","lat":44.02259,"lng":-92.86205},{"id":115375,"name":"Dodge Center","lat":44.02802,"lng":-92.85464},{"id":115429,"name":"Douglas County","lat":45.93372,"lng":-95.45352},{"id":115513,"name":"Duluth","lat":46.78327,"lng":-92.10658},{"id":115527,"name":"Dundas","lat":44.42941,"lng":-93.20188},{"id":115593,"name":"Eagan","lat":44.80413,"lng":-93.16689},{"id":115604,"name":"Eagle Lake","lat":44.16497,"lng":-93.88134},{"id":115634,"name":"East Bethel","lat":45.31941,"lng":-93.20245},{"id":115670,"name":"East Grand Forks","lat":47.92998,"lng":-97.02452},{"id":115676,"name":"East Gull Lake","lat":46.40802,"lng":-94.35584},{"id":115832,"name":"Eden Prairie","lat":44.85469,"lng":-93.47079},{"id":115833,"name":"Eden Valley","lat":45.32607,"lng":-94.54611},{"id":115849,"name":"Edgerton","lat":43.87247,"lng":-96.12864},{"id":115867,"name":"Edina","lat":44.88969,"lng":-93.34995},{"id":115946,"name":"Elbow Lake","lat":45.99413,"lng":-95.97672},{"id":115967,"name":"Elgin","lat":44.13024,"lng":-92.25156},{"id":115993,"name":"Elk River","lat":45.30385,"lng":-93.56718},{"id":116010,"name":"Elko New Market","lat":44.56472,"lng":-93.32694},{"id":116085,"name":"Ely","lat":47.90324,"lng":-91.86709},{"id":116185,"name":"Esko","lat":46.70578,"lng":-92.36325},{"id":116257,"name":"Eveleth","lat":47.46243,"lng":-92.53991},{"id":116269,"name":"Excelsior","lat":44.9033,"lng":-93.56635},{"id":116278,"name":"Eyota","lat":43.9883,"lng":-92.2285},{"id":116305,"name":"Fairfax","lat":44.52913,"lng":-94.72082},{"id":116337,"name":"Fairmont","lat":43.65218,"lng":-94.46108},{"id":116365,"name":"Falcon Heights","lat":44.99163,"lng":-93.16633},{"id":116397,"name":"Faribault","lat":44.29496,"lng":-93.26883},{"id":116398,"name":"Faribault County","lat":43.67393,"lng":-93.948},{"id":116419,"name":"Farmington","lat":44.64024,"lng":-93.14355},{"id":116479,"name":"Fergus Falls","lat":46.28302,"lng":-96.07756},{"id":116510,"name":"Fillmore","lat":43.674,"lng":-92.09017},{"id":116620,"name":"Foley","lat":45.66469,"lng":-93.9097},{"id":116661,"name":"Forest Lake","lat":45.27886,"lng":-92.98522},{"id":116773,"name":"Fosston","lat":47.57635,"lng":-95.75141},{"id":116882,"name":"Frazee","lat":46.72801,"lng":-95.70088},{"id":116899,"name":"Freeborn","lat":43.67384,"lng":-93.34882},{"id":116944,"name":"Fridley","lat":45.08608,"lng":-93.26328},{"id":116979,"name":"Fulda","lat":43.87052,"lng":-95.60029},{"id":117128,"name":"Gaylord","lat":44.55302,"lng":-94.22053},{"id":117203,"name":"Gilbert","lat":47.48882,"lng":-92.46491},{"id":117279,"name":"Glencoe","lat":44.76913,"lng":-94.15164},{"id":117315,"name":"Glenwood","lat":45.65024,"lng":-95.38976},{"id":117330,"name":"Glyndon","lat":46.87524,"lng":-96.57896},{"id":117355,"name":"Golden Valley","lat":45.00969,"lng":-93.34912},{"id":117379,"name":"Goodhue","lat":44.40052,"lng":-92.6238},{"id":117380,"name":"Goodhue County","lat":44.40985,"lng":-92.72259},{"id":117390,"name":"Goodview","lat":44.06246,"lng":-91.69571},{"id":117467,"name":"Grand Marais","lat":47.75045,"lng":-90.33427},{"id":117468,"name":"Grand Meadow","lat":43.7058,"lng":-92.57212},{"id":117472,"name":"Grand Rapids","lat":47.23717,"lng":-93.53021},{"id":117497,"name":"Granite Falls","lat":44.80996,"lng":-95.54558},{"id":117504,"name":"Grant","lat":45.08441,"lng":-92.91049},{"id":117513,"name":"Grant County","lat":45.93405,"lng":-96.01218},{"id":117651,"name":"Greenfield","lat":45.1033,"lng":-93.69135},{"id":117871,"name":"Hallock","lat":48.77443,"lng":-96.94645},{"id":117879,"name":"Ham Lake","lat":45.25024,"lng":-93.24995},{"id":117971,"name":"Hanover","lat":45.1558,"lng":-93.66635},{"id":118043,"name":"Harris","lat":45.58635,"lng":-92.97466},{"id":118132,"name":"Hastings","lat":44.7433,"lng":-92.85243},{"id":118168,"name":"Hawley","lat":46.88079,"lng":-96.31673},{"id":118185,"name":"Hayfield","lat":43.89052,"lng":-92.84769},{"id":118241,"name":"Hector","lat":44.74385,"lng":-94.71555},{"id":118291,"name":"Hennepin","lat":45.00458,"lng":-93.47688},{"id":118326,"name":"Hermantown","lat":46.80689,"lng":-92.23825},{"id":118359,"name":"Hibbing","lat":47.42715,"lng":-92.93769},{"id":118477,"name":"Hinckley","lat":46.01134,"lng":-92.94437},{"id":118652,"name":"Hopkins","lat":44.92496,"lng":-93.46273},{"id":118706,"name":"Houston County","lat":43.67144,"lng":-91.49283},{"id":118719,"name":"Howard Lake","lat":45.0608,"lng":-94.07331},{"id":118728,"name":"Hoyt Lakes","lat":47.51965,"lng":-92.13851},{"id":118732,"name":"Hubbard","lat":47.10865,"lng":-94.91664},{"id":118766,"name":"Hugo","lat":45.15997,"lng":-92.99327},{"id":118836,"name":"Hutchinson","lat":44.88774,"lng":-94.36971},{"id":118895,"name":"Independence","lat":45.02524,"lng":-93.70746},{"id":118952,"name":"International Falls","lat":48.60105,"lng":-93.41098},{"id":118953,"name":"Inver Grove Heights","lat":44.84802,"lng":-93.04272},{"id":119017,"name":"Isanti","lat":45.49024,"lng":-93.24773},{"id":119018,"name":"Isanti County","lat":45.56149,"lng":-93.29518},{"id":119041,"name":"Itasca","lat":47.50953,"lng":-93.632},{"id":119048,"name":"Ivanhoe","lat":44.4633,"lng":-96.24726},{"id":119070,"name":"Jackson","lat":43.62079,"lng":-94.9886},{"id":119092,"name":"Jackson County","lat":43.67417,"lng":-95.15411},{"id":119130,"name":"Janesville","lat":44.11608,"lng":-93.708},{"id":119315,"name":"Jordan","lat":44.66691,"lng":-93.6269},{"id":119373,"name":"Kanabec","lat":45.94522,"lng":-93.29343},{"id":119375,"name":"Kandiyohi","lat":45.15238,"lng":-95.00474},{"id":119392,"name":"Kasson","lat":44.02996,"lng":-92.75074},{"id":119424,"name":"Keewatin","lat":47.39966,"lng":-93.07242},{"id":119506,"name":"Kenyon","lat":44.27219,"lng":-92.98548},{"id":119667,"name":"Kittson","lat":48.77663,"lng":-96.78285},{"id":119705,"name":"Koochiching","lat":48.24527,"lng":-93.78337},{"id":119741,"name":"La Crescent","lat":43.82802,"lng":-91.30403},{"id":119811,"name":"Lac qui Parle","lat":44.99549,"lng":-96.17348},{"id":119894,"name":"Lake","lat":47.52317,"lng":-91.40885},{"id":119883,"name":"Lake City","lat":44.44968,"lng":-92.2682},{"id":119900,"name":"Lake Crystal","lat":44.1058,"lng":-94.21885},{"id":119905,"name":"Lake Elmo","lat":44.9958,"lng":-92.87938},{"id":120008,"name":"Lake of the Woods","lat":48.77051,"lng":-94.90503},{"id":119971,"name":"Lake Saint Croix Beach","lat":44.9208,"lng":-92.76687},{"id":119977,"name":"Lake Shore","lat":46.48552,"lng":-94.36056},{"id":120009,"name":"Lakefield","lat":43.67746,"lng":-95.17166},{"id":120015,"name":"Lakeland","lat":44.95636,"lng":-92.76576},{"id":120043,"name":"Lakeville","lat":44.64969,"lng":-93.24272},{"id":120178,"name":"Lauderdale","lat":44.99858,"lng":-93.20578},{"id":120257,"name":"Le Center","lat":44.38941,"lng":-93.73023},{"id":120264,"name":"Le Sueur","lat":44.46135,"lng":-93.91524},{"id":120265,"name":"Le Sueur County","lat":44.37143,"lng":-93.73008},{"id":120399,"name":"Lester Prairie","lat":44.88385,"lng":-94.04164},{"id":120425,"name":"Lewiston","lat":43.98441,"lng":-91.86932},{"id":120450,"name":"Lexington","lat":45.14247,"lng":-93.16328},{"id":120527,"name":"Lincoln County","lat":44.4126,"lng":-96.26709},{"id":120576,"name":"Lindstrom","lat":45.38941,"lng":-92.84799},{"id":120587,"name":"Lino Lakes","lat":45.16024,"lng":-93.08883},{"id":120605,"name":"Litchfield","lat":45.12718,"lng":-94.52805},{"id":120613,"name":"Little Canada","lat":45.02691,"lng":-93.08772},{"id":120617,"name":"Little Falls","lat":45.97635,"lng":-94.3625},{"id":120627,"name":"Little Rock","lat":47.86801,"lng":-95.11055},{"id":120747,"name":"Long Lake","lat":44.98663,"lng":-93.57162},{"id":120749,"name":"Long Prairie","lat":45.97469,"lng":-94.86558},{"id":120763,"name":"Lonsdale","lat":44.48024,"lng":-93.42856},{"id":120900,"name":"Luverne","lat":43.65414,"lng":-96.21281},{"id":120938,"name":"Lyon","lat":44.41349,"lng":-95.83897},{"id":120979,"name":"Madelia","lat":44.05079,"lng":-94.4183},{"id":120994,"name":"Madison","lat":45.00968,"lng":-96.19588},{"id":121022,"name":"Madison Lake","lat":44.20441,"lng":-93.81551},{"id":121043,"name":"Mahnomen","lat":47.31524,"lng":-95.96865},{"id":121044,"name":"Mahnomen County","lat":47.32524,"lng":-95.80905},{"id":121047,"name":"Mahtomedi","lat":45.06969,"lng":-92.9516},{"id":121130,"name":"Mankato","lat":44.15906,"lng":-94.00915},{"id":121159,"name":"Mantorville","lat":44.06913,"lng":-92.75575},{"id":121167,"name":"Maple Grove","lat":45.07246,"lng":-93.45579},{"id":121169,"name":"Maple Lake","lat":45.22913,"lng":-94.00192},{"id":121171,"name":"Maple Plain","lat":45.00719,"lng":-93.65579},{"id":121175,"name":"Mapleton","lat":43.92885,"lng":-93.95606},{"id":121178,"name":"Maplewood","lat":44.95302,"lng":-92.99522},{"id":121308,"name":"Marshall","lat":44.4469,"lng":-95.78835},{"id":121320,"name":"Marshall County","lat":48.35813,"lng":-96.36847},{"id":121341,"name":"Martin","lat":43.67436,"lng":-94.55107},{"id":121432,"name":"Mayer","lat":44.88496,"lng":-93.88775},{"id":121535,"name":"McLeod","lat":44.82354,"lng":-94.27242},{"id":121593,"name":"Medford","lat":44.17413,"lng":-93.24632},{"id":121604,"name":"Medina","lat":45.03524,"lng":-93.58246},{"id":121614,"name":"Meeker","lat":45.12312,"lng":-94.52731},{"id":121629,"name":"Melrose","lat":45.67469,"lng":-94.80752},{"id":121644,"name":"Menahga","lat":46.75385,"lng":-95.09808},{"id":121658,"name":"Mendota Heights","lat":44.88358,"lng":-93.13827},{"id":121832,"name":"Milaca","lat":45.7558,"lng":-93.65441},{"id":121876,"name":"Mille Lacs","lat":45.93805,"lng":-93.63009},{"id":121951,"name":"Minneapolis","lat":44.97997,"lng":-93.26384},{"id":121955,"name":"Minneota","lat":44.55885,"lng":-95.98559},{"id":121956,"name":"Minnetonka","lat":44.9133,"lng":-93.50329},{"id":121957,"name":"Minnetonka Mills","lat":44.94107,"lng":-93.4419},{"id":121958,"name":"Minnetrista","lat":44.9383,"lng":-93.71774},{"id":122126,"name":"Montevideo","lat":44.94803,"lng":-95.71701},{"id":122134,"name":"Montgomery","lat":44.43885,"lng":-93.58134},{"id":122167,"name":"Monticello","lat":45.30552,"lng":-93.79414},{"id":122180,"name":"Montrose","lat":45.06496,"lng":-93.91108},{"id":122212,"name":"Moorhead","lat":46.87386,"lng":-96.76951},{"id":122214,"name":"Moose Lake","lat":46.45411,"lng":-92.76187},{"id":122218,"name":"Mora","lat":45.8769,"lng":-93.29384},{"id":122268,"name":"Morris","lat":45.58607,"lng":-95.91394},{"id":122277,"name":"Morrison","lat":46.01262,"lng":-94.26842},{"id":122318,"name":"Mound","lat":44.93663,"lng":-93.66607},{"id":122326,"name":"Mounds View","lat":45.10497,"lng":-93.20856},{"id":122419,"name":"Mountain Iron","lat":47.53243,"lng":-92.62351},{"id":122420,"name":"Mountain Lake","lat":43.93885,"lng":-94.92971},{"id":122445,"name":"Mower","lat":43.67147,"lng":-92.75251},{"id":122495,"name":"Murray","lat":44.02212,"lng":-95.76328},{"id":122671,"name":"New Brighton","lat":45.06552,"lng":-93.20189},{"id":122726,"name":"New Hope","lat":45.03802,"lng":-93.38662},{"id":122743,"name":"New London","lat":45.30108,"lng":-94.94418},{"id":122766,"name":"New Prague","lat":44.5433,"lng":-93.57607},{"id":122769,"name":"New Richland","lat":43.89385,"lng":-93.49383},{"id":122788,"name":"New Ulm","lat":44.31246,"lng":-94.46053},{"id":122797,"name":"New York Mills","lat":46.51802,"lng":-95.37615},{"id":122845,"name":"Newport","lat":44.86636,"lng":-93.00049},{"id":122895,"name":"Nicollet","lat":44.27608,"lng":-94.18746},{"id":122896,"name":"Nicollet County","lat":44.34989,"lng":-94.2473},{"id":122908,"name":"Nisswa","lat":46.52052,"lng":-94.28861},{"id":122920,"name":"Nobles","lat":43.67424,"lng":-95.75339},{"id":122950,"name":"Norman","lat":47.32648,"lng":-96.45528},{"id":122994,"name":"North Branch","lat":45.51135,"lng":-92.98022},{"id":123063,"name":"North Mankato","lat":44.1733,"lng":-94.03385},{"id":123073,"name":"North Oaks","lat":45.10274,"lng":-93.07911},{"id":123098,"name":"North Saint Paul","lat":45.01247,"lng":-92.99188},{"id":123152,"name":"Northfield","lat":44.4583,"lng":-93.1616},{"id":123202,"name":"Norwood (historical)","lat":44.76802,"lng":-93.92747},{"id":123203,"name":"Norwood Young America","lat":44.77357,"lng":-93.92163},{"id":123211,"name":"Nowthen","lat":45.32802,"lng":-93.47023},{"id":123239,"name":"Oak Grove","lat":45.3408,"lng":-93.3269},{"id":123258,"name":"Oak Park Heights","lat":45.03136,"lng":-92.79298},{"id":123271,"name":"Oakdale","lat":44.96302,"lng":-92.96494},{"id":123303,"name":"Oakport","lat":46.93191,"lng":-96.77897},{"id":123450,"name":"Olivia","lat":44.77635,"lng":-94.98972},{"id":123454,"name":"Olmsted","lat":44.00375,"lng":-92.40177},{"id":123573,"name":"Orono","lat":44.97135,"lng":-93.6044},{"id":123575,"name":"Oronoco","lat":44.16608,"lng":-92.53491},{"id":123584,"name":"Ortonville","lat":45.30469,"lng":-96.44478},{"id":123592,"name":"Osakis","lat":45.86691,"lng":-95.15225},{"id":123614,"name":"Osseo","lat":45.11941,"lng":-93.40245},{"id":123633,"name":"Otsego","lat":45.27413,"lng":-93.59135},{"id":123641,"name":"Otter Tail","lat":46.4088,"lng":-95.708},{"id":123659,"name":"Owatonna","lat":44.08385,"lng":-93.22604},{"id":123850,"name":"Park Rapids","lat":46.92218,"lng":-95.05863},{"id":123866,"name":"Parkers Prairie","lat":46.15302,"lng":-95.32892},{"id":123880,"name":"Parkville","lat":47.53104,"lng":-92.57907},{"id":123947,"name":"Paynesville","lat":45.38052,"lng":-94.71195},{"id":123996,"name":"Pelican Rapids","lat":46.57079,"lng":-96.08311},{"id":124030,"name":"Pennington","lat":48.06623,"lng":-96.03667},{"id":124056,"name":"Pequot Lakes","lat":46.60302,"lng":-94.30944},{"id":124059,"name":"Perham","lat":46.5944,"lng":-95.57254},{"id":124181,"name":"Pierz","lat":45.98163,"lng":-94.10471},{"id":124219,"name":"Pine","lat":46.12077,"lng":-92.74127},{"id":124218,"name":"Pine City","lat":45.82607,"lng":-92.96854},{"id":124228,"name":"Pine Island","lat":44.20135,"lng":-92.6463},{"id":124277,"name":"Pipestone","lat":44.00053,"lng":-96.31753},{"id":124278,"name":"Pipestone County","lat":44.023,"lng":-96.25864},{"id":124328,"name":"Plainview","lat":44.16497,"lng":-92.17156},{"id":124405,"name":"Plymouth","lat":45.01052,"lng":-93.45551},{"id":124448,"name":"Polk","lat":47.77385,"lng":-96.40181},{"id":124483,"name":"Pope","lat":45.58602,"lng":-95.44448},{"id":124656,"name":"Preston","lat":43.67024,"lng":-92.08322},{"id":124688,"name":"Princeton","lat":45.56997,"lng":-93.58163},{"id":124698,"name":"Prior Lake","lat":44.7133,"lng":-93.42273},{"id":124700,"name":"Proctor","lat":46.74716,"lng":-92.22547},{"id":124841,"name":"Ramsey","lat":45.2611,"lng":-93.45},{"id":124843,"name":"Ramsey County","lat":45.01706,"lng":-93.09961},{"id":124949,"name":"Red Lake","lat":47.87635,"lng":-95.01694},{"id":124950,"name":"Red Lake County","lat":47.87169,"lng":-96.0953},{"id":124951,"name":"Red Lake Falls","lat":47.88219,"lng":-96.27421},{"id":124963,"name":"Red Wing","lat":44.56247,"lng":-92.5338},{"id":124965,"name":"Redby","lat":47.87857,"lng":-94.91305},{"id":124987,"name":"Redwood","lat":44.40366,"lng":-95.25383},{"id":124988,"name":"Redwood Falls","lat":44.5394,"lng":-95.11694},{"id":125027,"name":"Renville","lat":44.78913,"lng":-95.21167},{"id":125028,"name":"Renville County","lat":44.72681,"lng":-94.94714},{"id":125052,"name":"Rice","lat":45.75191,"lng":-94.22027},{"id":125054,"name":"Rice County","lat":44.35426,"lng":-93.29668},{"id":125061,"name":"Richfield","lat":44.8833,"lng":-93.283},{"id":125094,"name":"Richmond","lat":45.45413,"lng":-94.51833},{"id":125236,"name":"Robbinsdale","lat":45.03219,"lng":-93.33856},{"id":125266,"name":"Rochester","lat":44.02163,"lng":-92.4699},{"id":125272,"name":"Rock","lat":43.67463,"lng":-96.25321},{"id":125276,"name":"Rock Creek","lat":45.75746,"lng":-92.96243},{"id":125302,"name":"Rockford","lat":45.0883,"lng":-93.73441},{"id":125324,"name":"Rockville","lat":45.47191,"lng":-94.34083},{"id":125350,"name":"Rogers","lat":45.18885,"lng":-93.55301},{"id":125407,"name":"Roseau","lat":48.84609,"lng":-95.76277},{"id":125408,"name":"Roseau County","lat":48.77514,"lng":-95.81082},{"id":125432,"name":"Rosemount","lat":44.73941,"lng":-93.12577},{"id":125440,"name":"Roseville","lat":45.00608,"lng":-93.15661},{"id":125496,"name":"Royalton","lat":45.82997,"lng":-94.29361},{"id":125519,"name":"Rush City","lat":45.68551,"lng":-92.96549},{"id":125523,"name":"Rushford","lat":43.8083,"lng":-91.75293},{"id":125601,"name":"Saint Anthony","lat":45.02052,"lng":-93.218},{"id":125603,"name":"Saint Augusta","lat":45.4583,"lng":-94.19804},{"id":125610,"name":"Saint Bonifacius","lat":44.90552,"lng":-93.74746},{"id":125615,"name":"Saint Charles","lat":43.96941,"lng":-92.06433},{"id":125627,"name":"Saint Cloud","lat":45.5608,"lng":-94.16249},{"id":125633,"name":"Saint Francis","lat":45.38691,"lng":-93.3594},{"id":125655,"name":"Saint James","lat":43.98246,"lng":-94.62692},{"id":125674,"name":"Saint Joseph","lat":45.56496,"lng":-94.31833},{"id":125682,"name":"Saint Louis","lat":47.58986,"lng":-92.46147},{"id":125683,"name":"Saint Louis Park","lat":44.9483,"lng":-93.34801},{"id":125697,"name":"Saint Michael","lat":45.20996,"lng":-93.66496},{"id":125703,"name":"Saint Paul","lat":44.94441,"lng":-93.09327},{"id":125705,"name":"Saint Paul Park","lat":44.84219,"lng":-92.99132},{"id":125708,"name":"Saint Peter","lat":44.32358,"lng":-93.95801},{"id":125874,"name":"Sandstone","lat":46.13106,"lng":-92.86742},{"id":125953,"name":"Sartell","lat":45.62163,"lng":-94.20694},{"id":125962,"name":"Sauk Centre","lat":45.73747,"lng":-94.95252},{"id":125965,"name":"Sauk Rapids","lat":45.59191,"lng":-94.1661},{"id":125972,"name":"Savage","lat":44.77913,"lng":-93.33634},{"id":125995,"name":"Scandia","lat":45.25358,"lng":-92.80577},{"id":126052,"name":"Scott","lat":44.64846,"lng":-93.53593},{"id":126209,"name":"Shafer","lat":45.38691,"lng":-92.74771},{"id":126211,"name":"Shakopee","lat":44.79802,"lng":-93.5269},{"id":126314,"name":"Sherburn","lat":43.65218,"lng":-94.72692},{"id":126316,"name":"Sherburne","lat":45.44395,"lng":-93.77459},{"id":126369,"name":"Shoreview","lat":45.07913,"lng":-93.14717},{"id":126371,"name":"Shorewood","lat":44.9008,"lng":-93.58912},{"id":126392,"name":"Sibley","lat":44.57948,"lng":-94.23216},{"id":126420,"name":"Silver Bay","lat":47.29436,"lng":-91.25739},{"id":126495,"name":"Slayton","lat":43.98774,"lng":-95.75585},{"id":126496,"name":"Sleepy Eye","lat":44.29718,"lng":-94.72415},{"id":126721,"name":"South Saint Paul","lat":44.89274,"lng":-93.03494},{"id":126834,"name":"Spicer","lat":45.23302,"lng":-94.94001},{"id":126859,"name":"Spring Grove","lat":43.56108,"lng":-91.63598},{"id":126869,"name":"Spring Lake Park","lat":45.10774,"lng":-93.238},{"id":126871,"name":"Spring Park","lat":44.93524,"lng":-93.63218},{"id":126876,"name":"Spring Valley","lat":43.68691,"lng":-92.38906},{"id":126902,"name":"Springfield","lat":44.23885,"lng":-94.97582},{"id":126931,"name":"Stacy","lat":45.39802,"lng":-92.98744},{"id":126975,"name":"Staples","lat":46.35552,"lng":-94.79224},{"id":126983,"name":"Starbuck","lat":45.6144,"lng":-95.53115},{"id":127005,"name":"Stearns","lat":45.55215,"lng":-94.61302},{"id":127010,"name":"Steele County","lat":44.02234,"lng":-93.22604},{"id":127040,"name":"Stevens","lat":45.58613,"lng":-96.0003},{"id":127055,"name":"Stewartville","lat":43.85552,"lng":-92.48851},{"id":127061,"name":"Stillwater","lat":45.05636,"lng":-92.80604},{"id":127345,"name":"Swift","lat":45.28271,"lng":-95.68143},{"id":127462,"name":"Taylors Falls","lat":45.40191,"lng":-92.65243},{"id":127574,"name":"Thief River Falls","lat":48.11914,"lng":-96.18115},{"id":127693,"name":"Todd","lat":46.07062,"lng":-94.8976},{"id":127720,"name":"Tonka Bay","lat":44.90857,"lng":-93.59301},{"id":127770,"name":"Tracy","lat":44.23329,"lng":-95.61918},{"id":127785,"name":"Traverse","lat":45.77218,"lng":-96.47164},{"id":127855,"name":"Truman","lat":43.82773,"lng":-94.43719},{"id":127935,"name":"Two Harbors","lat":47.02271,"lng":-91.67073},{"id":127941,"name":"Tyler","lat":44.2783,"lng":-96.13475},{"id":128073,"name":"Vadnais Heights","lat":45.05747,"lng":-93.07383},{"id":128222,"name":"Victoria","lat":44.85857,"lng":-93.66163},{"id":128271,"name":"Vineland","lat":46.16357,"lng":-93.75747},{"id":128287,"name":"Virginia","lat":47.52326,"lng":-92.53657},{"id":128312,"name":"Wabasha","lat":44.38386,"lng":-92.03294},{"id":128313,"name":"Wabasha County","lat":44.28428,"lng":-92.23027},{"id":128317,"name":"Waconia","lat":44.8508,"lng":-93.78691},{"id":128321,"name":"Wadena","lat":46.44246,"lng":-95.13614},{"id":128322,"name":"Wadena County","lat":46.58576,"lng":-94.96941},{"id":128353,"name":"Waite Park","lat":45.55719,"lng":-94.22416},{"id":128385,"name":"Walker","lat":47.10135,"lng":-94.58722},{"id":128448,"name":"Wanamingo","lat":44.30441,"lng":-92.79047},{"id":128482,"name":"Warren","lat":48.19664,"lng":-96.77284},{"id":128514,"name":"Warroad","lat":48.90527,"lng":-95.3144},{"id":128530,"name":"Waseca","lat":44.07774,"lng":-93.50744},{"id":128531,"name":"Waseca County","lat":44.02212,"lng":-93.58728},{"id":128570,"name":"Washington County","lat":45.03873,"lng":-92.88396},{"id":128622,"name":"Watertown","lat":44.96357,"lng":-93.84719},{"id":128627,"name":"Waterville","lat":44.21885,"lng":-93.568},{"id":128637,"name":"Watonwan","lat":43.97843,"lng":-94.61406},{"id":128670,"name":"Waverly","lat":45.06663,"lng":-93.96636},{"id":128713,"name":"Wayzata","lat":44.97413,"lng":-93.50662},{"id":128782,"name":"Wells","lat":43.74607,"lng":-93.72884},{"id":128852,"name":"West Coon Rapids","lat":45.15969,"lng":-93.34967},{"id":128972,"name":"West Saint Paul","lat":44.91608,"lng":-93.10161},{"id":129114,"name":"Wheaton","lat":45.80441,"lng":-96.49923},{"id":129126,"name":"White Bear Lake","lat":45.08469,"lng":-93.00994},{"id":129248,"name":"Wilkin","lat":46.35708,"lng":-96.46835},{"id":129303,"name":"Willmar","lat":45.12191,"lng":-95.04334},{"id":129375,"name":"Windom","lat":43.86635,"lng":-95.11694},{"id":129406,"name":"Winnebago","lat":43.76773,"lng":-94.16579},{"id":129424,"name":"Winona","lat":44.04996,"lng":-91.63932},{"id":129425,"name":"Winona County","lat":43.98685,"lng":-91.77913},{"id":129431,"name":"Winsted","lat":44.96385,"lng":-94.04747},{"id":129451,"name":"Winthrop","lat":44.54302,"lng":-94.36637},{"id":129509,"name":"Woodbury","lat":44.92386,"lng":-92.95938},{"id":129598,"name":"Worthington","lat":43.61996,"lng":-95.5964},{"id":129610,"name":"Wright","lat":45.17393,"lng":-93.96305},{"id":129637,"name":"Wyoming","lat":45.33636,"lng":-92.99716},{"id":129678,"name":"Yellow Medicine","lat":44.71625,"lng":-95.86836},{"id":129713,"name":"Young America (historical)","lat":44.78274,"lng":-93.91358},{"id":129756,"name":"Zimmerman","lat":45.4433,"lng":-93.58996},{"id":129761,"name":"Zumbrota","lat":44.29413,"lng":-92.66908}]