[{"id":48454,"name":"Beeford","lat":53.96999,"lng":-0.28913},{"id":48470,"name":"Bempton","lat":54.13036,"lng":-0.17853},{"id":48486,"name":"Beverley","lat":53.84587,"lng":-0.42332},{"id":48660,"name":"Brandesburton","lat":53.9111,"lng":-0.30122},{"id":48687,"name":"Bridlington","lat":54.08306,"lng":-0.19192},{"id":48949,"name":"Cherry Burton","lat":53.86667,"lng":-0.5},{"id":49326,"name":"Driffield","lat":54.00613,"lng":-0.44495},{"id":49360,"name":"Dunnington","lat":53.95,"lng":-0.25},{"id":49385,"name":"East Ayton","lat":54.2548,"lng":-0.47483},{"id":49410,"name":"East Riding of Yorkshire","lat":53.91667,"lng":-0.5},{"id":49425,"name":"Eastrington","lat":53.76038,"lng":-0.79325},{"id":49453,"name":"Ellerker","lat":53.75323,"lng":-0.60416},{"id":49490,"name":"Etton","lat":53.87848,"lng":-0.51314},{"id":49553,"name":"Filey","lat":54.21,"lng":-0.28917},{"id":49567,"name":"Flamborough","lat":54.11487,"lng":-0.12274},{"id":49640,"name":"Gilberdyke","lat":53.75297,"lng":-0.73892},{"id":49866,"name":"Hayton","lat":53.9,"lng":-0.75},{"id":50004,"name":"Hotham","lat":53.79583,"lng":-0.64253},{"id":50024,"name":"Hunmanby","lat":54.17957,"lng":-0.32007},{"id":50144,"name":"Kilham","lat":54.06413,"lng":-0.38057},{"id":50266,"name":"Leconfield","lat":53.8773,"lng":-0.45729},{"id":50332,"name":"Little Weighton","lat":53.79021,"lng":-0.50679},{"id":50383,"name":"Lockington","lat":53.91415,"lng":-0.48572},{"id":50437,"name":"Lund","lat":53.9192,"lng":-0.52211},{"id":50505,"name":"Market Weighton","lat":53.8631,"lng":-0.66505},{"id":50658,"name":"Nafferton","lat":54.01965,"lng":-0.3919},{"id":50750,"name":"North Cave","lat":53.78012,"lng":-0.64965},{"id":50760,"name":"North Newbald","lat":53.81667,"lng":-0.61667},{"id":50928,"name":"Pocklington","lat":53.93335,"lng":-0.78106},{"id":51081,"name":"Rillington","lat":54.15779,"lng":-0.69494},{"id":51208,"name":"Scalby","lat":53.76667,"lng":-0.71667},{"id":51210,"name":"Scarborough","lat":54.27966,"lng":-0.40443},{"id":51325,"name":"Skipsea","lat":53.97674,"lng":-0.22084},{"id":51347,"name":"South Cave","lat":53.76987,"lng":-0.60107},{"id":51620,"name":"Tickton","lat":53.86233,"lng":-0.3833},{"id":51694,"name":"Ulrome","lat":53.99198,"lng":-0.22968},{"id":51731,"name":"Walkington","lat":53.8195,"lng":-0.48958},{"id":51854,"name":"Wetwang","lat":54.0175,"lng":-0.57738},{"id":51958,"name":"Wold Newton","lat":54.1428,"lng":-0.39993}]