[{"id":48587,"name":"Bolton","lat":53.58333,"lng":-2.43333},{"id":48600,"name":"Borough of Bury","lat":53.58333,"lng":-2.33333},{"id":48798,"name":"Bury","lat":53.6,"lng":-2.3},{"id":49437,"name":"Edenfield","lat":53.66674,"lng":-2.30481},{"id":49533,"name":"Farnworth","lat":53.55,"lng":-2.4},{"id":50330,"name":"Little Lever","lat":53.56346,"lng":-2.37803},{"id":51016,"name":"Radcliffe","lat":53.56178,"lng":-2.32455},{"id":51026,"name":"Ramsbottom","lat":53.64789,"lng":-2.31683},{"id":51042,"name":"Rawtenstall","lat":53.70076,"lng":-2.28442},{"id":51111,"name":"Rossendale","lat":53.68456,"lng":-2.2769},{"id":51651,"name":"Tottington","lat":53.61326,"lng":-2.34071},{"id":51872,"name":"Whitefield","lat":53.55,"lng":-2.3}]