[{"id":129903,"name":"Beshariq","lat":40.43583,"lng":70.61028},{"id":129923,"name":"Fergana","lat":40.38421,"lng":71.78432},{"id":129932,"name":"Hamza","lat":40.42762,"lng":71.50534},{"id":129948,"name":"Kirguli","lat":40.43553,"lng":71.76721},{"id":129955,"name":"Marg‘ilon","lat":40.47237,"lng":71.72463},{"id":129969,"name":"Oltiariq","lat":40.39194,"lng":71.47417},{"id":129986,"name":"Qo‘qon","lat":40.52861,"lng":70.9425},{"id":129988,"name":"Quva","lat":40.52204,"lng":72.07292},{"id":129989,"name":"Quvasoy","lat":40.29721,"lng":71.98026},{"id":129992,"name":"Rishton","lat":40.35667,"lng":71.28472},{"id":130000,"name":"Shohimardon","lat":39.98322,"lng":71.80512},{"id":130004,"name":"So‘x Tumani","lat":40.04417,"lng":71.09417},{"id":130008,"name":"Toshloq","lat":40.47722,"lng":71.76778},{"id":130019,"name":"Yangi Marg‘ilon","lat":40.42722,"lng":71.71889},{"id":130025,"name":"Yaypan","lat":40.37583,"lng":70.81556}]