[{"id":62291,"name":"Aboukir","lat":18.2509,"lng":-77.34327},{"id":62300,"name":"Alderton","lat":18.28706,"lng":-77.20832},{"id":62301,"name":"Alexandria","lat":18.30411,"lng":-77.35311},{"id":62308,"name":"Alva","lat":18.29679,"lng":-77.31717},{"id":62329,"name":"Bamboo","lat":18.39216,"lng":-77.26429},{"id":62345,"name":"Beecher Town","lat":18.38465,"lng":-77.11617},{"id":62352,"name":"Bensonton","lat":18.22315,"lng":-77.20861},{"id":62364,"name":"Blackstonedge","lat":18.27357,"lng":-77.04254},{"id":62373,"name":"Bohemia","lat":18.21239,"lng":-77.46954},{"id":62376,"name":"Borobridge","lat":18.19779,"lng":-77.42755},{"id":62396,"name":"Browns Town","lat":18.38464,"lng":-77.35286},{"id":62412,"name":"Calderwood","lat":18.25641,"lng":-77.27144},{"id":62424,"name":"Cascade","lat":18.23209,"lng":-77.46255},{"id":62435,"name":"Cave Valley","lat":18.23268,"lng":-77.36337},{"id":62442,"name":"Chalky Hill","lat":18.37964,"lng":-77.1752},{"id":62451,"name":"Chester","lat":18.44786,"lng":-77.26503},{"id":62456,"name":"Claremont","lat":18.32556,"lng":-77.20643},{"id":62464,"name":"Cole Gate","lat":18.37967,"lng":-77.08518},{"id":62477,"name":"Content Garden","lat":18.40977,"lng":-77.0754},{"id":62494,"name":"Cuffie Ridge","lat":18.22793,"lng":-77.42054},{"id":62514,"name":"Discovery Bay","lat":18.43725,"lng":-77.41815},{"id":62542,"name":"Epworth","lat":18.36083,"lng":-77.13342},{"id":62545,"name":"Exchange","lat":18.37265,"lng":-77.06572},{"id":62549,"name":"Faith's Pen","lat":18.22963,"lng":-77.08804},{"id":62583,"name":"Gibraltar","lat":18.35079,"lng":-77.42142},{"id":62593,"name":"Golden Grove","lat":18.32956,"lng":-77.12256},{"id":62607,"name":"Great Pond","lat":18.40227,"lng":-77.08511},{"id":62647,"name":"Higgin Land","lat":18.34119,"lng":-77.27072},{"id":62650,"name":"Hinds Town","lat":18.35425,"lng":-77.09812},{"id":62662,"name":"Inverness","lat":18.27531,"lng":-77.36862},{"id":62710,"name":"Lime Hall","lat":18.39742,"lng":-77.21051},{"id":62711,"name":"Lime Tree Gardens","lat":18.34545,"lng":-77.38645},{"id":62714,"name":"Linton Park","lat":18.26081,"lng":-77.42221},{"id":62737,"name":"Macknie","lat":18.21191,"lng":-77.28016},{"id":62738,"name":"Madras","lat":18.29112,"lng":-77.44875},{"id":62751,"name":"Mansfield","lat":18.40265,"lng":-77.09488},{"id":62783,"name":"Moneague","lat":18.28307,"lng":-77.13855},{"id":62798,"name":"Mount Moriah","lat":18.20617,"lng":-77.44094},{"id":62803,"name":"Mount Zion","lat":18.43377,"lng":-77.28028},{"id":62835,"name":"Ocho Rios","lat":18.4076,"lng":-77.10312},{"id":62855,"name":"Parry Town","lat":18.38359,"lng":-77.10345},{"id":62881,"name":"Philadelphia","lat":18.40005,"lng":-77.32735},{"id":62883,"name":"Pimento Walk","lat":18.39578,"lng":-77.11383},{"id":62903,"name":"Priory","lat":18.4366,"lng":-77.24551},{"id":62935,"name":"River Head","lat":18.2603,"lng":-77.07782},{"id":62959,"name":"Runaway Bay","lat":18.45962,"lng":-77.3357},{"id":62962,"name":"Saint Ann’s Bay","lat":18.43581,"lng":-77.20098},{"id":63019,"name":"St. Ann's Bay","lat":18.42989,"lng":-77.20775},{"id":63020,"name":"St. D'Acre","lat":18.333,"lng":-77.36297},{"id":63029,"name":"Steer Town","lat":18.42852,"lng":-77.17101},{"id":63037,"name":"Sturge Town","lat":18.41631,"lng":-77.31988},{"id":63081,"name":"Walkers Wood","lat":18.31939,"lng":-77.07082},{"id":63093,"name":"Watt Town","lat":18.29427,"lng":-77.41466},{"id":63126,"name":"York Castle","lat":18.27515,"lng":-77.22923}]