[{"id":130184,"name":"Cao Lãnh","lat":10.46017,"lng":105.63294},{"id":130266,"name":"Huyện Cái Bè","lat":10.38824,"lng":105.9462},{"id":130241,"name":"Huyện Cai Lậy","lat":10.38943,"lng":106.06774},{"id":130252,"name":"Huyện Châu Thành","lat":10.386,"lng":106.27311},{"id":130260,"name":"Huyện Chợ Gạo","lat":10.37373,"lng":106.44341},{"id":130293,"name":"Huyện Gò Công Đông","lat":10.36784,"lng":106.74592},{"id":130292,"name":"Huyện Gò Công Tây","lat":10.34527,"lng":106.59851},{"id":130340,"name":"Huyện Lai Vung","lat":10.24051,"lng":105.66327},{"id":130351,"name":"Huyện Lấp Vò","lat":10.35918,"lng":105.60611},{"id":130430,"name":"Huyện Tam Nông","lat":10.72761,"lng":105.52522},{"id":130483,"name":"Huyện Tân Hồng","lat":10.87089,"lng":105.49104},{"id":130486,"name":"Huyện Tân Phước","lat":10.51489,"lng":106.23312},{"id":130435,"name":"Huyện Thanh Bình","lat":10.60137,"lng":105.47811},{"id":130443,"name":"Huyện Tháp Mười","lat":10.54398,"lng":105.81875},{"id":130574,"name":"Mỹ Tho","lat":10.36004,"lng":106.35996},{"id":130589,"name":"Sa Dec","lat":10.29085,"lng":105.75635},{"id":130599,"name":"Thành Phố Mỹ Tho","lat":10.36221,"lng":106.36824},{"id":130607,"name":"Thị Trấn Tân Thành","lat":10.25616,"lng":105.5928},{"id":130610,"name":"Thị Xã Gò Công","lat":10.40005,"lng":106.65847}]