[{"id":9280,"name":"Borovan","lat":43.446358,"lng":23.7354316},{"id":9295,"name":"Byala Slatina","lat":43.46667,"lng":23.93333},{"id":9344,"name":"Hayredin","lat":43.60193,"lng":23.66135},{"id":9373,"name":"Kozloduy","lat":43.77864,"lng":23.72058},{"id":9376,"name":"Krivodol","lat":43.37444,"lng":23.48444},{"id":9400,"name":"Mezdra","lat":43.15,"lng":23.7},{"id":9403,"name":"Mizia","lat":43.68623,"lng":23.85371},{"id":9434,"name":"Obshtina Borovan","lat":43.43333,"lng":23.75},{"id":9488,"name":"Obshtina Hayredin","lat":43.58333,"lng":23.66667},{"id":9510,"name":"Obshtina Kozloduy","lat":43.71667,"lng":23.73333},{"id":9513,"name":"Obshtina Krivodol","lat":43.38333,"lng":23.48333},{"id":9531,"name":"Obshtina Mezdra","lat":43.13333,"lng":23.73333},{"id":9534,"name":"Obshtina Mizia","lat":43.63333,"lng":23.85},{"id":9546,"name":"Obshtina Oryahovo","lat":43.69038,"lng":23.98643},{"id":9574,"name":"Obshtina Roman","lat":43.15,"lng":23.91667},{"id":9631,"name":"Obshtina Vratsa","lat":43.28333,"lng":23.6},{"id":9643,"name":"Oryahovo","lat":43.73618,"lng":23.96052},{"id":9672,"name":"Roman","lat":43.1463767,"lng":23.9254908},{"id":9742,"name":"Vratsa","lat":43.21,"lng":23.5625}]