[{"id":52148,"name":"Aburi","lat":5.84802,"lng":-0.17449},{"id":52152,"name":"Akim Oda","lat":5.92665,"lng":-0.98577},{"id":52153,"name":"Akim Swedru","lat":5.8938,"lng":-1.01636},{"id":52154,"name":"Akropong","lat":5.97462,"lng":-0.08542},{"id":52155,"name":"Akwatia","lat":6.04024,"lng":-0.80876},{"id":52158,"name":"Asamankese","lat":5.86006,"lng":-0.6635},{"id":52163,"name":"Begoro","lat":6.38706,"lng":-0.37738},{"id":52182,"name":"Kibi","lat":6.16494,"lng":-0.55376},{"id":52184,"name":"Koforidua","lat":6.09408,"lng":-0.25913},{"id":52191,"name":"Mpraeso","lat":6.59321,"lng":-0.73462},{"id":52194,"name":"Nsawam","lat":5.80893,"lng":-0.35026},{"id":52203,"name":"Suhum","lat":6.04089,"lng":-0.45004}]